odoo9_addon_auth_brute_force-9.0.1.1.0-py2.7-nspkg.pth
odoo9_addon_auth_brute_force-9.0.1.1.0.dist-info/DESCRIPTION.rst
odoo9_addon_auth_brute_force-9.0.1.1.0.dist-info/METADATA
odoo9_addon_auth_brute_force-9.0.1.1.0.dist-info/RECORD
odoo9_addon_auth_brute_force-9.0.1.1.0.dist-info/WHEEL
odoo9_addon_auth_brute_force-9.0.1.1.0.dist-info/metadata.json
odoo9_addon_auth_brute_force-9.0.1.1.0.dist-info/namespace_packages.txt
odoo9_addon_auth_brute_force-9.0.1.1.0.dist-info/top_level.txt
odoo_addons/auth_brute_force/README.rst
odoo_addons/auth_brute_force/__init__.py
odoo_addons/auth_brute_force/__openerp__.py
odoo_addons/auth_brute_force/i18n/am.po
odoo_addons/auth_brute_force/i18n/ar.po
odoo_addons/auth_brute_force/i18n/bg.po
odoo_addons/auth_brute_force/i18n/bs.po
odoo_addons/auth_brute_force/i18n/ca.po
odoo_addons/auth_brute_force/i18n/cs.po
odoo_addons/auth_brute_force/i18n/da.po
odoo_addons/auth_brute_force/i18n/de.po
odoo_addons/auth_brute_force/i18n/el_GR.po
odoo_addons/auth_brute_force/i18n/en_GB.po
odoo_addons/auth_brute_force/i18n/es.po
odoo_addons/auth_brute_force/i18n/es_AR.po
odoo_addons/auth_brute_force/i18n/es_CL.po
odoo_addons/auth_brute_force/i18n/es_CO.po
odoo_addons/auth_brute_force/i18n/es_CR.po
odoo_addons/auth_brute_force/i18n/es_DO.po
odoo_addons/auth_brute_force/i18n/es_EC.po
odoo_addons/auth_brute_force/i18n/es_ES.po
odoo_addons/auth_brute_force/i18n/es_MX.po
odoo_addons/auth_brute_force/i18n/es_PE.po
odoo_addons/auth_brute_force/i18n/es_PY.po
odoo_addons/auth_brute_force/i18n/es_VE.po
odoo_addons/auth_brute_force/i18n/et.po
odoo_addons/auth_brute_force/i18n/eu.po
odoo_addons/auth_brute_force/i18n/fa.po
odoo_addons/auth_brute_force/i18n/fi.po
odoo_addons/auth_brute_force/i18n/fr.po
odoo_addons/auth_brute_force/i18n/fr_CA.po
odoo_addons/auth_brute_force/i18n/fr_CH.po
odoo_addons/auth_brute_force/i18n/gl.po
odoo_addons/auth_brute_force/i18n/gl_ES.po
odoo_addons/auth_brute_force/i18n/he.po
odoo_addons/auth_brute_force/i18n/hr.po
odoo_addons/auth_brute_force/i18n/hr_HR.po
odoo_addons/auth_brute_force/i18n/hu.po
odoo_addons/auth_brute_force/i18n/id.po
odoo_addons/auth_brute_force/i18n/it.po
odoo_addons/auth_brute_force/i18n/ja.po
odoo_addons/auth_brute_force/i18n/ko.po
odoo_addons/auth_brute_force/i18n/lt.po
odoo_addons/auth_brute_force/i18n/lt_LT.po
odoo_addons/auth_brute_force/i18n/lv.po
